{
    "swagger": "2.0",
    "info": {
        "description": "This is api gateway",
        "termsOfService": "https://t.me/husanmusa",
        "contact": {}
    },
    "paths": {
        "/book": {
            "get": {
                "description": "List Book",
                "consumes": [
                    "application/json"
                ],
                "produces": [
                    "application/json"
                ],
                "tags": [
                    "Book"
                ],
                "summary": "List Book",
                "operationId": "list_book",
                "parameters": [
                    {
                        "type": "integer",
                        "description": "offset",
                        "name": "offset",
                        "in": "query"
                    },
                    {
                        "type": "integer",
                        "description": "limit",
                        "name": "limit",
                        "in": "query"
                    }
                ],
                "responses": {
                    "200": {
                        "description": "ListBookResponseBody",
                        "schema": {
                            "$ref": "#/definitions/models.Books"
                        }
                    },
                    "400": {
                        "description": "Invalid Argument",
                        "schema": {
                            "allOf": [
                                {
                                    "$ref": "#/definitions/response.SuccessModel"
                                },
                                {
                                    "type": "object",
                                    "properties": {
                                        "data": {
                                            "type": "string"
                                        }
                                    }
                                }
                            ]
                        }
                    },
                    "500": {
                        "description": "Server Error",
                        "schema": {
                            "allOf": [
                                {
                                    "$ref": "#/definitions/response.SuccessModel"
                                },
                                {
                                    "type": "object",
                                    "properties": {
                                        "data": {
                                            "type": "string"
                                        }
                                    }
                                }
                            ]
                        }
                    }
                }
            },
            "post": {
                "description": "Create Book",
                "consumes": [
                    "application/json"
                ],
                "produces": [
                    "application/json"
                ],
                "tags": [
                    "Book"
                ],
                "summary": "Create Book",
                "operationId": "create_book",
                "parameters": [
                    {
                        "description": "CreateBookRequestBody",
                        "name": "book",
                        "in": "body",
                        "required": true,
                        "schema": {
                            "$ref": "#/definitions/models.CreateBook"
                        }
                    }
                ],
                "responses": {
                    "201": {
                        "description": "Book data",
                        "schema": {
                            "$ref": "#/definitions/models.BookResponse"
                        }
                    },
                    "400": {
                        "description": "Bad Request",
                        "schema": {
                            "allOf": [
                                {
                                    "$ref": "#/definitions/response.SuccessModel"
                                },
                                {
                                    "type": "object",
                                    "properties": {
                                        "data": {
                                            "type": "string"
                                        }
                                    }
                                }
                            ]
                        }
                    },
                    "500": {
                        "description": "Server Error",
                        "schema": {
                            "allOf": [
                                {
                                    "$ref": "#/definitions/response.SuccessModel"
                                },
                                {
                                    "type": "object",
                                    "properties": {
                                        "data": {
                                            "type": "string"
                                        }
                                    }
                                }
                            ]
                        }
                    }
                }
            }
        },
        "/book/user/{id}": {
            "get": {
                "description": "List Book User",
                "consumes": [
                    "application/json"
                ],
                "produces": [
                    "application/json"
                ],
                "tags": [
                    "Book"
                ],
                "summary": "List Book User",
                "operationId": "list_book_by_user_id",
                "parameters": [
                    {
                        "type": "string",
                        "description": "id",
                        "name": "id",
                        "in": "path"
                    }
                ],
                "responses": {
                    "200": {
                        "description": "ListBookResponseBody",
                        "schema": {
                            "$ref": "#/definitions/models.Books"
                        }
                    },
                    "400": {
                        "description": "Invalid Argument",
                        "schema": {
                            "allOf": [
                                {
                                    "$ref": "#/definitions/response.SuccessModel"
                                },
                                {
                                    "type": "object",
                                    "properties": {
                                        "data": {
                                            "type": "string"
                                        }
                                    }
                                }
                            ]
                        }
                    },
                    "500": {
                        "description": "Server Error",
                        "schema": {
                            "allOf": [
                                {
                                    "$ref": "#/definitions/response.SuccessModel"
                                },
                                {
                                    "type": "object",
                                    "properties": {
                                        "data": {
                                            "type": "string"
                                        }
                                    }
                                }
                            ]
                        }
                    }
                }
            }
        },
        "/book/{id}": {
            "get": {
                "description": "Get Book",
                "consumes": [
                    "application/json"
                ],
                "produces": [
                    "application/json"
                ],
                "tags": [
                    "Book"
                ],
                "summary": "Get Book",
                "operationId": "get_book",
                "parameters": [
                    {
                        "type": "string",
                        "description": "Book ID",
                        "name": "id",
                        "in": "path",
                        "required": true
                    }
                ],
                "responses": {
                    "200": {
                        "description": "Book data",
                        "schema": {
                            "$ref": "#/definitions/models.Book"
                        }
                    },
                    "400": {
                        "description": "Bad Request",
                        "schema": {
                            "allOf": [
                                {
                                    "$ref": "#/definitions/response.SuccessModel"
                                },
                                {
                                    "type": "object",
                                    "properties": {
                                        "data": {
                                            "type": "string"
                                        }
                                    }
                                }
                            ]
                        }
                    },
                    "500": {
                        "description": "Server Error",
                        "schema": {
                            "allOf": [
                                {
                                    "$ref": "#/definitions/response.SuccessModel"
                                },
                                {
                                    "type": "object",
                                    "properties": {
                                        "data": {
                                            "type": "string"
                                        }
                                    }
                                }
                            ]
                        }
                    }
                }
            },
            "put": {
                "description": "Update Book",
                "consumes": [
                    "application/json"
                ],
                "produces": [
                    "application/json"
                ],
                "tags": [
                    "Book"
                ],
                "summary": "Update Book",
                "operationId": "update_book",
                "parameters": [
                    {
                        "type": "string",
                        "description": "Book ID",
                        "name": "id",
                        "in": "path",
                        "required": true
                    },
                    {
                        "description": "UpdateBookRequestBody",
                        "name": "book",
                        "in": "body",
                        "required": true,
                        "schema": {
                            "$ref": "#/definitions/models.CreateBook"
                        }
                    }
                ],
                "responses": {
                    "200": {
                        "description": "Book data",
                        "schema": {
                            "$ref": "#/definitions/models.Book"
                        }
                    },
                    "400": {
                        "description": "Bad Request",
                        "schema": {
                            "allOf": [
                                {
                                    "$ref": "#/definitions/response.SuccessModel"
                                },
                                {
                                    "type": "object",
                                    "properties": {
                                        "data": {
                                            "type": "string"
                                        }
                                    }
                                }
                            ]
                        }
                    },
                    "500": {
                        "description": "Server Error",
                        "schema": {
                            "allOf": [
                                {
                                    "$ref": "#/definitions/response.SuccessModel"
                                },
                                {
                                    "type": "object",
                                    "properties": {
                                        "data": {
                                            "type": "string"
                                        }
                                    }
                                }
                            ]
                        }
                    }
                }
            },
            "delete": {
                "description": "Delete Book",
                "consumes": [
                    "application/json"
                ],
                "produces": [
                    "application/json"
                ],
                "tags": [
                    "Book"
                ],
                "summary": "Delete Book",
                "operationId": "delete_book",
                "parameters": [
                    {
                        "type": "string",
                        "description": "Book ID",
                        "name": "id",
                        "in": "path",
                        "required": true
                    }
                ],
                "responses": {
                    "200": {
                        "description": "Book data",
                        "schema": {
                            "allOf": [
                                {
                                    "$ref": "#/definitions/response.SuccessModel"
                                },
                                {
                                    "type": "object",
                                    "properties": {
                                        "data": {
                                            "type": "string"
                                        }
                                    }
                                }
                            ]
                        }
                    },
                    "400": {
                        "description": "Bad Request",
                        "schema": {
                            "allOf": [
                                {
                                    "$ref": "#/definitions/response.SuccessModel"
                                },
                                {
                                    "type": "object",
                                    "properties": {
                                        "data": {
                                            "type": "string"
                                        }
                                    }
                                }
                            ]
                        }
                    },
                    "500": {
                        "description": "Server Error",
                        "schema": {
                            "allOf": [
                                {
                                    "$ref": "#/definitions/response.SuccessModel"
                                },
                                {
                                    "type": "object",
                                    "properties": {
                                        "data": {
                                            "type": "string"
                                        }
                                    }
                                }
                            ]
                        }
                    }
                }
            }
        },
        "/sale": {
            "get": {
                "description": "List SaleBook",
                "consumes": [
                    "application/json"
                ],
                "produces": [
                    "application/json"
                ],
                "tags": [
                    "SaleBook"
                ],
                "summary": "List SaleBook",
                "operationId": "list_sale_book",
                "parameters": [
                    {
                        "type": "integer",
                        "description": "offset",
                        "name": "offset",
                        "in": "query"
                    },
                    {
                        "type": "integer",
                        "description": "limit",
                        "name": "limit",
                        "in": "query"
                    }
                ],
                "responses": {
                    "200": {
                        "description": "ListSaleBookResponseBody",
                        "schema": {
                            "$ref": "#/definitions/models.SaleBooks"
                        }
                    },
                    "400": {
                        "description": "Invalid Argument",
                        "schema": {
                            "allOf": [
                                {
                                    "$ref": "#/definitions/response.SuccessModel"
                                },
                                {
                                    "type": "object",
                                    "properties": {
                                        "data": {
                                            "type": "string"
                                        }
                                    }
                                }
                            ]
                        }
                    },
                    "500": {
                        "description": "Server Error",
                        "schema": {
                            "allOf": [
                                {
                                    "$ref": "#/definitions/response.SuccessModel"
                                },
                                {
                                    "type": "object",
                                    "properties": {
                                        "data": {
                                            "type": "string"
                                        }
                                    }
                                }
                            ]
                        }
                    }
                }
            },
            "post": {
                "description": "Create SaleBook",
                "consumes": [
                    "application/json"
                ],
                "produces": [
                    "application/json"
                ],
                "tags": [
                    "SaleBook"
                ],
                "summary": "Create SaleBook",
                "operationId": "create_sale_book",
                "parameters": [
                    {
                        "description": "CreateSaleBookRequestBody",
                        "name": "sale",
                        "in": "body",
                        "required": true,
                        "schema": {
                            "$ref": "#/definitions/models.CreateSaleBook"
                        }
                    }
                ],
                "responses": {
                    "201": {
                        "description": "SaleBook data",
                        "schema": {
                            "$ref": "#/definitions/models.SaleBook"
                        }
                    },
                    "400": {
                        "description": "Bad Request",
                        "schema": {
                            "allOf": [
                                {
                                    "$ref": "#/definitions/response.SuccessModel"
                                },
                                {
                                    "type": "object",
                                    "properties": {
                                        "data": {
                                            "type": "string"
                                        }
                                    }
                                }
                            ]
                        }
                    },
                    "500": {
                        "description": "Server Error",
                        "schema": {
                            "allOf": [
                                {
                                    "$ref": "#/definitions/response.SuccessModel"
                                },
                                {
                                    "type": "object",
                                    "properties": {
                                        "data": {
                                            "type": "string"
                                        }
                                    }
                                }
                            ]
                        }
                    }
                }
            }
        },
        "/sale/{id}": {
            "get": {
                "description": "Get SaleBook",
                "consumes": [
                    "application/json"
                ],
                "produces": [
                    "application/json"
                ],
                "tags": [
                    "SaleBook"
                ],
                "summary": "Get SaleBook",
                "operationId": "get_sale_book",
                "parameters": [
                    {
                        "type": "string",
                        "description": "SaleBook ID",
                        "name": "id",
                        "in": "path",
                        "required": true
                    }
                ],
                "responses": {
                    "200": {
                        "description": "SaleBook data",
                        "schema": {
                            "$ref": "#/definitions/models.SaleBook"
                        }
                    },
                    "400": {
                        "description": "Bad Request",
                        "schema": {
                            "allOf": [
                                {
                                    "$ref": "#/definitions/response.SuccessModel"
                                },
                                {
                                    "type": "object",
                                    "properties": {
                                        "data": {
                                            "type": "string"
                                        }
                                    }
                                }
                            ]
                        }
                    },
                    "500": {
                        "description": "Server Error",
                        "schema": {
                            "allOf": [
                                {
                                    "$ref": "#/definitions/response.SuccessModel"
                                },
                                {
                                    "type": "object",
                                    "properties": {
                                        "data": {
                                            "type": "string"
                                        }
                                    }
                                }
                            ]
                        }
                    }
                }
            },
            "put": {
                "description": "Update SaleBook",
                "consumes": [
                    "application/json"
                ],
                "produces": [
                    "application/json"
                ],
                "tags": [
                    "SaleBook"
                ],
                "summary": "Update SaleBook",
                "operationId": "update_sale_book",
                "parameters": [
                    {
                        "type": "string",
                        "description": "SaleBook ID",
                        "name": "id",
                        "in": "path",
                        "required": true
                    },
                    {
                        "description": "UpdateSaleBookRequestBody",
                        "name": "sale",
                        "in": "body",
                        "required": true,
                        "schema": {
                            "$ref": "#/definitions/models.CreateSaleBook"
                        }
                    }
                ],
                "responses": {
                    "200": {
                        "description": "SaleBook data",
                        "schema": {
                            "$ref": "#/definitions/models.SaleBook"
                        }
                    },
                    "400": {
                        "description": "Bad Request",
                        "schema": {
                            "allOf": [
                                {
                                    "$ref": "#/definitions/response.SuccessModel"
                                },
                                {
                                    "type": "object",
                                    "properties": {
                                        "data": {
                                            "type": "string"
                                        }
                                    }
                                }
                            ]
                        }
                    },
                    "500": {
                        "description": "Server Error",
                        "schema": {
                            "allOf": [
                                {
                                    "$ref": "#/definitions/response.SuccessModel"
                                },
                                {
                                    "type": "object",
                                    "properties": {
                                        "data": {
                                            "type": "string"
                                        }
                                    }
                                }
                            ]
                        }
                    }
                }
            },
            "delete": {
                "description": "Delete SaleBook",
                "consumes": [
                    "application/json"
                ],
                "produces": [
                    "application/json"
                ],
                "tags": [
                    "SaleBook"
                ],
                "summary": "Delete SaleBook",
                "operationId": "delete_sale_book",
                "parameters": [
                    {
                        "type": "string",
                        "description": "SaleBook ID",
                        "name": "id",
                        "in": "path",
                        "required": true
                    }
                ],
                "responses": {
                    "200": {
                        "description": "SaleBook data",
                        "schema": {
                            "allOf": [
                                {
                                    "$ref": "#/definitions/response.SuccessModel"
                                },
                                {
                                    "type": "object",
                                    "properties": {
                                        "data": {
                                            "type": "string"
                                        }
                                    }
                                }
                            ]
                        }
                    },
                    "400": {
                        "description": "Bad Request",
                        "schema": {
                            "allOf": [
                                {
                                    "$ref": "#/definitions/response.SuccessModel"
                                },
                                {
                                    "type": "object",
                                    "properties": {
                                        "data": {
                                            "type": "string"
                                        }
                                    }
                                }
                            ]
                        }
                    },
                    "500": {
                        "description": "Server Error",
                        "schema": {
                            "allOf": [
                                {
                                    "$ref": "#/definitions/response.SuccessModel"
                                },
                                {
                                    "type": "object",
                                    "properties": {
                                        "data": {
                                            "type": "string"
                                        }
                                    }
                                }
                            ]
                        }
                    }
                }
            }
        },
        "/user": {
            "get": {
                "description": "List User",
                "consumes": [
                    "application/json"
                ],
                "produces": [
                    "application/json"
                ],
                "tags": [
                    "User"
                ],
                "summary": "List User",
                "operationId": "list_user",
                "parameters": [
                    {
                        "type": "integer",
                        "description": "offset",
                        "name": "offset",
                        "in": "query"
                    },
                    {
                        "type": "integer",
                        "description": "limit",
                        "name": "limit",
                        "in": "query"
                    }
                ],
                "responses": {
                    "200": {
                        "description": "User data",
                        "schema": {
                            "$ref": "#/definitions/models.UsersResponse"
                        }
                    },
                    "400": {
                        "description": "Bad Request",
                        "schema": {
                            "allOf": [
                                {
                                    "$ref": "#/definitions/response.SuccessModel"
                                },
                                {
                                    "type": "object",
                                    "properties": {
                                        "data": {
                                            "type": "string"
                                        }
                                    }
                                }
                            ]
                        }
                    },
                    "500": {
                        "description": "Server Error",
                        "schema": {
                            "allOf": [
                                {
                                    "$ref": "#/definitions/response.SuccessModel"
                                },
                                {
                                    "type": "object",
                                    "properties": {
                                        "data": {
                                            "type": "string"
                                        }
                                    }
                                }
                            ]
                        }
                    }
                }
            },
            "post": {
                "description": "Create User",
                "consumes": [
                    "application/json"
                ],
                "produces": [
                    "application/json"
                ],
                "tags": [
                    "User"
                ],
                "summary": "Create User",
                "operationId": "create_user",
                "parameters": [
                    {
                        "description": "CreateUserRequestBody",
                        "name": "user",
                        "in": "body",
                        "required": true,
                        "schema": {
                            "$ref": "#/definitions/models.CreateUser"
                        }
                    }
                ],
                "responses": {
                    "201": {
                        "description": "User data",
                        "schema": {
                            "$ref": "#/definitions/models.User"
                        }
                    },
                    "400": {
                        "description": "Bad Request",
                        "schema": {
                            "allOf": [
                                {
                                    "$ref": "#/definitions/response.SuccessModel"
                                },
                                {
                                    "type": "object",
                                    "properties": {
                                        "data": {
                                            "type": "string"
                                        }
                                    }
                                }
                            ]
                        }
                    },
                    "500": {
                        "description": "Server Error",
                        "schema": {
                            "allOf": [
                                {
                                    "$ref": "#/definitions/response.SuccessModel"
                                },
                                {
                                    "type": "object",
                                    "properties": {
                                        "data": {
                                            "type": "string"
                                        }
                                    }
                                }
                            ]
                        }
                    }
                }
            }
        },
        "/user/find_book/{id}": {
            "get": {
                "description": "List User",
                "consumes": [
                    "application/json"
                ],
                "produces": [
                    "application/json"
                ],
                "tags": [
                    "User"
                ],
                "summary": "List User has a book",
                "operationId": "find_book",
                "parameters": [
                    {
                        "type": "string",
                        "description": "id",
                        "name": "id",
                        "in": "path",
                        "required": true
                    }
                ],
                "responses": {
                    "200": {
                        "description": "ListUserResponseBody",
                        "schema": {
                            "$ref": "#/definitions/models.Users"
                        }
                    },
                    "400": {
                        "description": "Bad Request",
                        "schema": {
                            "allOf": [
                                {
                                    "$ref": "#/definitions/response.SuccessModel"
                                },
                                {
                                    "type": "object",
                                    "properties": {
                                        "data": {
                                            "type": "string"
                                        }
                                    }
                                }
                            ]
                        }
                    },
                    "500": {
                        "description": "Server Error",
                        "schema": {
                            "allOf": [
                                {
                                    "$ref": "#/definitions/response.SuccessModel"
                                },
                                {
                                    "type": "object",
                                    "properties": {
                                        "data": {
                                            "type": "string"
                                        }
                                    }
                                }
                            ]
                        }
                    }
                }
            }
        },
        "/user/{id}": {
            "get": {
                "description": "Get User",
                "consumes": [
                    "application/json"
                ],
                "produces": [
                    "application/json"
                ],
                "tags": [
                    "User"
                ],
                "summary": "Get User",
                "operationId": "get_user",
                "parameters": [
                    {
                        "type": "string",
                        "description": "User ID",
                        "name": "id",
                        "in": "path",
                        "required": true
                    }
                ],
                "responses": {
                    "200": {
                        "description": "User data",
                        "schema": {
                            "$ref": "#/definitions/models.UserResponse"
                        }
                    },
                    "400": {
                        "description": "Bad Request",
                        "schema": {
                            "allOf": [
                                {
                                    "$ref": "#/definitions/response.SuccessModel"
                                },
                                {
                                    "type": "object",
                                    "properties": {
                                        "data": {
                                            "type": "string"
                                        }
                                    }
                                }
                            ]
                        }
                    },
                    "500": {
                        "description": "Server Error",
                        "schema": {
                            "allOf": [
                                {
                                    "$ref": "#/definitions/response.SuccessModel"
                                },
                                {
                                    "type": "object",
                                    "properties": {
                                        "data": {
                                            "type": "string"
                                        }
                                    }
                                }
                            ]
                        }
                    }
                }
            },
            "put": {
                "description": "Update User",
                "consumes": [
                    "application/json"
                ],
                "produces": [
                    "application/json"
                ],
                "tags": [
                    "User"
                ],
                "summary": "Update User",
                "operationId": "update_user",
                "parameters": [
                    {
                        "type": "string",
                        "description": "User ID",
                        "name": "id",
                        "in": "path",
                        "required": true
                    },
                    {
                        "description": "UpdateUserRequestBody",
                        "name": "user",
                        "in": "body",
                        "required": true,
                        "schema": {
                            "$ref": "#/definitions/models.User"
                        }
                    }
                ],
                "responses": {
                    "200": {
                        "description": "User data",
                        "schema": {
                            "$ref": "#/definitions/models.User"
                        }
                    },
                    "400": {
                        "description": "Bad Request",
                        "schema": {
                            "allOf": [
                                {
                                    "$ref": "#/definitions/response.SuccessModel"
                                },
                                {
                                    "type": "object",
                                    "properties": {
                                        "data": {
                                            "type": "string"
                                        }
                                    }
                                }
                            ]
                        }
                    },
                    "500": {
                        "description": "Server Error",
                        "schema": {
                            "allOf": [
                                {
                                    "$ref": "#/definitions/response.SuccessModel"
                                },
                                {
                                    "type": "object",
                                    "properties": {
                                        "data": {
                                            "type": "string"
                                        }
                                    }
                                }
                            ]
                        }
                    }
                }
            },
            "delete": {
                "description": "Delete User",
                "consumes": [
                    "application/json"
                ],
                "produces": [
                    "application/json"
                ],
                "tags": [
                    "User"
                ],
                "summary": "Delete User",
                "operationId": "delete_user",
                "parameters": [
                    {
                        "type": "string",
                        "description": "User ID",
                        "name": "id",
                        "in": "path",
                        "required": true
                    }
                ],
                "responses": {
                    "200": {
                        "description": "User data",
                        "schema": {
                            "allOf": [
                                {
                                    "$ref": "#/definitions/response.SuccessModel"
                                },
                                {
                                    "type": "object",
                                    "properties": {
                                        "data": {
                                            "type": "string"
                                        }
                                    }
                                }
                            ]
                        }
                    },
                    "400": {
                        "description": "Bad Request",
                        "schema": {
                            "allOf": [
                                {
                                    "$ref": "#/definitions/response.SuccessModel"
                                },
                                {
                                    "type": "object",
                                    "properties": {
                                        "data": {
                                            "type": "string"
                                        }
                                    }
                                }
                            ]
                        }
                    },
                    "500": {
                        "description": "Server Error",
                        "schema": {
                            "allOf": [
                                {
                                    "$ref": "#/definitions/response.SuccessModel"
                                },
                                {
                                    "type": "object",
                                    "properties": {
                                        "data": {
                                            "type": "string"
                                        }
                                    }
                                }
                            ]
                        }
                    }
                }
            }
        }
    },
    "definitions": {
        "models.Book": {
            "type": "object",
            "properties": {
                "author": {
                    "type": "string"
                },
                "count": {
                    "type": "integer"
                },
                "created_at": {
                    "type": "string"
                },
                "deleted_at": {
                    "type": "string"
                },
                "id": {
                    "type": "string"
                },
                "name": {
                    "type": "string"
                },
                "published_date": {
                    "type": "string"
                },
                "updated_at": {
                    "type": "string"
                }
            }
        },
        "models.BookResponse": {
            "type": "object",
            "properties": {
                "data": {
                    "$ref": "#/definitions/models.Book"
                },
                "description": {
                    "type": "string"
                },
                "status": {
                    "type": "string"
                }
            }
        },
        "models.Books": {
            "type": "object",
            "properties": {
                "books": {
                    "type": "array",
                    "items": {
                        "$ref": "#/definitions/models.Book"
                    }
                }
            }
        },
        "models.CreateBook": {
            "type": "object",
            "properties": {
                "author": {
                    "type": "string"
                },
                "count": {
                    "type": "integer"
                },
                "name": {
                    "type": "string"
                },
                "published_date": {
                    "type": "string"
                }
            }
        },
        "models.CreateSaleBook": {
            "type": "object",
            "properties": {
                "book_id": {
                    "type": "string"
                },
                "user_id": {
                    "type": "string"
                }
            }
        },
        "models.CreateUser": {
            "type": "object",
            "properties": {
                "email": {
                    "type": "string"
                },
                "first_name": {
                    "type": "string"
                },
                "last_name": {
                    "type": "string"
                },
                "middle_name": {
                    "type": "string"
                },
                "phone": {
                    "type": "string"
                }
            }
        },
        "models.SaleBook": {
            "type": "object",
            "properties": {
                "book_id": {
                    "type": "string"
                },
                "id": {
                    "type": "string"
                },
                "user_id": {
                    "type": "string"
                }
            }
        },
        "models.SaleBooks": {
            "type": "object",
            "properties": {
                "sale_books": {
                    "type": "array",
                    "items": {
                        "$ref": "#/definitions/models.SaleBook"
                    }
                }
            }
        },
        "models.User": {
            "type": "object",
            "properties": {
                "email": {
                    "type": "string"
                },
                "first_name": {
                    "type": "string"
                },
                "id": {
                    "type": "string"
                },
                "last_name": {
                    "type": "string"
                },
                "middle_name": {
                    "type": "string"
                },
                "phone": {
                    "type": "string"
                }
            }
        },
        "models.UserResponse": {
            "type": "object",
            "properties": {
                "data": {
                    "$ref": "#/definitions/models.User"
                },
                "description": {
                    "type": "string"
                },
                "status": {
                    "type": "string"
                }
            }
        },
        "models.Users": {
            "type": "object",
            "properties": {
                "users": {
                    "type": "array",
                    "items": {
                        "$ref": "#/definitions/models.User"
                    }
                }
            }
        },
        "models.UsersResponse": {
            "type": "object",
            "properties": {
                "data": {
                    "$ref": "#/definitions/models.Users"
                },
                "description": {
                    "type": "string"
                },
                "status": {
                    "type": "string"
                }
            }
        },
        "response.SuccessModel": {
            "type": "object",
            "properties": {
                "code": {
                    "type": "string"
                },
                "data": {},
                "message": {
                    "type": "string"
                }
            }
        }
    }
}